ipsum/__init__.py
ipsum/corpus.py
ipsum/exceptions.py
ipsum/model/__init__.py
ipsum/model/choices.py
ipsum/model/language.py
ipsum/model/markov_chain.py
ipsum/parse/__init__.py
ipsum/parse/language/bg.py
ipsum/parse/language/de.py
ipsum/parse/language/el.py
ipsum/parse/language/en.py
ipsum/parse/language/es.py
ipsum/parse/language/fr.py
ipsum/parse/language/it.py
ipsum/parse/language/mk.py
ipsum/parse/language/nl.py
ipsum/parse/language/sq.py
ipsum/parse/language/sr.py
ipsum/parse/language/sv.py
ipsum/parse/parser.py
ipsum/parse/sentencizer.py
ipsum/parse/skeletonizer.py
ipsum/parse/standardizer.py
ipsum/parse/worderizer.py
ipsum/py.typed
ipsum/supported_languages.py
ipsum/trained_models/bg.zip
ipsum/trained_models/de.zip
ipsum/trained_models/el.zip
ipsum/trained_models/en.zip
ipsum/trained_models/es.zip
ipsum/trained_models/fr.zip
ipsum/trained_models/it.zip
ipsum/trained_models/mk.zip
ipsum/trained_models/nl.zip
ipsum/trained_models/sq.zip
ipsum/trained_models/sr.zip
ipsum/trained_models/sv.zip
ipsum/utils.py
ipsum-0.1.1.dist-info/LICENSE.md
ipsum-0.1.1.dist-info/WHEEL
ipsum-0.1.1.dist-info/METADATA
ipsum-0.1.1.dist-info/entry_points.txt
ipsum-0.1.1.dist-info/RECORD
