Metadata-Version: 2.1
Name: ipsum
Version: 0.1.1
Summary: Library for procedurally-generating text that resembles a particular language.
License: MIT
Author: Darko Trifunovski
Author-email: darko@trifunovski.me
Requires-Python: >=3.8.1,<4.0.0
Classifier: License :: OSI Approved :: MIT License
Classifier: Programming Language :: Python :: 3
Classifier: Programming Language :: Python :: 3.9
Classifier: Programming Language :: Python :: 3.10
Classifier: Programming Language :: Python :: 3.11
Requires-Dist: typing-extensions (>=4.4.0,<5.0.0)
